ngi_code_academy/Habib/calc.py
ngi_code_academy/__init__.py
ngi_code_academy/amanda/calc.py
ngi_code_academy/chunli/cal.py
ngi_code_academy/henrik/calc.py
ngi_code_academy/martyna/calc.py
ngi_code_academy/ole/calc.py
ngi_code_academy/truls/calc_truls.py
ngi_code_academy-0.3.81.dist-info/LICENSE
ngi_code_academy-0.3.81.dist-info/METADATA
ngi_code_academy-0.3.81.dist-info/WHEEL
ngi_code_academy-0.3.81.dist-info/RECORD
