Metadata-Version: 2.3
Name: ngi-code-academy
Version: 0.3.81
Summary: An example package for use in courses!
Author: Ole-Jakob Olsen
Author-email: ole.jakob.olsen@ngi.no
Requires-Python: >=3.11,<4.0
Classifier: Programming Language :: Python :: 3
Classifier: Programming Language :: Python :: 3.11
Classifier: Programming Language :: Python :: 3.12
Classifier: Programming Language :: Python :: 3.13
